ipv4_range/IPv4Range.py
ipv4_range/__init__.py
ipv4_range-0.1.1.dist-info/METADATA
ipv4_range-0.1.1.dist-info/WHEEL
ipv4_range-0.1.1.dist-info/entry_points.txt
ipv4_range-0.1.1.dist-info/RECORD
