Metadata-Version: 2.4
Name: ipv4-range
Version: 0.1.1
Summary: IPv4Range creates objects like be 10.0.0.0-10.0.0.101
Author-email: Nikolai Vasilenko <nikolai-vasilenko-developer@yandex.ru>
Requires-Python: >=3.11
